coda/__init__.py
coda/sdk/__init__.py
coda/sdk/constants.py
coda/sdk/enums.py
coda/sdk/essence.py
coda/sdk/job.py
coda/sdk/preset.py
coda/sdk/utils.py
coda/sdk/workflow.py
coda/tc_tools.py
sprocket_systems_coda_sdk-2.0.7.dist-info/METADATA
sprocket_systems_coda_sdk-2.0.7.dist-info/WHEEL
sprocket_systems_coda_sdk-2.0.7.dist-info/entry_points.txt
sprocket_systems_coda_sdk-2.0.7.dist-info/licenses/LICENSE
sprocket_systems_coda_sdk-2.0.7.dist-info/RECORD
